{
  "_id" : ObjectId("5bd3292c64aa33a460bcdade"),
  "name" : "Test Exhibition",
  "description" : "Test Description",
  "rooms" : [
    {
      "text" : "Room #1",
      "floor" : "WOOD",
      "ceiling": "CONCRETE",
      "exhibits" : [],
      "position" : {
        "x" : 0.0,
        "y" : 0.0,
        "z" : 0.0
      },
      "entrypoint" : {
        "x" : 5.0,
        "y" : 5.0,
        "z" : 5.0
      },
      "size" : {
        "x" : 10.0,
        "y" : 10.0,
        "z" : 10.0
      },
      "walls" : [
        {
          "direction" : "NORTH",
          "color" : {
            "x" : 0.70,
            "y" : 0.70,
            "z" : 0.70
          },
          "texture":"NONE",
          "exhibits" : [
            {
              "name" : "Rembrandt 01",
              "description" : "Lorem ipsum dolor sit amet",
              "path" : "5bd3292c64aa33a460bcdade/1/N/D_001128.jpg",
              "type" : "IMAGE",
              "size" : {
                "x" : 2.000,
                "y" : 1.55,
                "z" : 1.0
              },
              "position" : {
                "x" : 1.5,
                "y" : 1.75,
                "z" : 0.0
              }
            },
            {
              "name" : "Rembrandt 02",
              "description" : "Lorem ipsum dolor sit amet",
              "path" : "5bd3292c64aa33a460bcdade/1/N/D_005219.jpg",
              "type" : "IMAGE",
              "size" : {
                "x" : 2.000,
                "y" : 1.634,
                "z" : 1.0
              },
              "position" : {
                "x" : 4.5,
                "y" : 1.5,
                "z" : 0.0
              }
            },
            {
              "name" : "Rembrandt 03",
              "description" : "Lorem ipsum dolor sit amet",
              "path" : "5bd3292c64aa33a460bcdade/1/N/D_005221.jpg",
              "type" : "IMAGE",
              "size" : {
                "x" : 1.468,
                "y" : 2.000,
                "z" : 1.0
              },
              "position" : {
                "x" : 8.5,
                "y" : 1.75,
                "z" : 0.0
              }
            }
          ]
        },
        {
          "direction" : "EAST",
          "color" : {
            "x" : 0.0,
            "y" : 0.0,
            "z" : 0.0
          },
          "texture":"BRICKS",
          "exhibits" : [
            {
              "name" : "Bodies In The Air",
              "description" : "Lorem ipsum dolor sit amet",
              "path" : "5bd3292c64aa33a460bcdade/1/E/2007_0570_04.jpg",
              "type" : "IMAGE",
              "size" : {
                "x" : 2.512,
                "y" : 2.0,
                "z" : 1.0
              },
              "position" : {
                "x" : 8.0,
                "y" : 1.25,
                "z" : 0.0
              }
            }
          ]
        },
        {
          "direction" : "SOUTH",
          "color" : {
            "x" : 0.0,
            "y" : 0.0,
            "z" : 0.0
          },
          "texture":"CONCRETE",
          "exhibits" : [
            {
              "name" : "Technik",
              "description" : "Lorem ipsum dolor sit amet",
              "path" : "5bd3292c64aa33a460bcdade/1/S/D_001258.jpg",
              "type" : "IMAGE",
              "size" : {
                "x" : 1.568,
                "y" : 2.0,
                "z" : 1.0
              },
              "position" : {
                "x" : 3.5,
                "y" : 1.5,
                "z" : 0.0
              }
            },
            {
              "name" : "Technik",
              "description" : "Lorem ipsum dolor sit amet",
              "path" : "5bd3292c64aa33a460bcdade/1/S/D_013000.jpg",
              "type" : "IMAGE",
              "size" : {
                "x" : 2.507,
                "y" : 2.0,
                "z" : 1.0
              },
              "position" : {
                "x" : 7.5,
                "y" : 1.5,
                "z" : 0.0
              }
            }
          ]
        },
        {
          "direction" : "WEST",
          "color" : {
            "x" : 0.0,
            "y" : 0.0,
            "z" : 0.0
          },
          "texture":"NONE",
          "exhibits" : []
        }
      ]
    }
  ]
}